speck/__init__.py
speck/cache.py
speck/client.py
speck/errors.py
speck/etc/cities_p.json
speck/types/__init__.py
speck/types/data_point.py
speck/types/raw.py
speck_wrapper-0.3.12.dist-info/LICENSE
speck_wrapper-0.3.12.dist-info/METADATA
speck_wrapper-0.3.12.dist-info/WHEEL
speck_wrapper-0.3.12.dist-info/top_level.txt
speck_wrapper-0.3.12.dist-info/RECORD
