Metadata-Version: 2.1
Name: speck-wrapper
Version: 0.3.12
Summary: A simple wrapper and frontend for weatherAPI.com
Home-page: https://github.com/schctl/speck
Author: Nevin Jose, Sachin Cherian
License: MIT
Platform: UNKNOWN
Requires-Python: >=3.6.0
Requires-Dist: requests
Provides-Extra: docs
Requires-Dist: sphinx ; extra == 'docs'
Requires-Dist: sphinx-press-theme ; extra == 'docs'
Provides-Extra: tests
Requires-Dist: pytest ; extra == 'tests'
